AppCategorizer/__init__.py
AppCategorizer/categorizer.py
AppCategorizer/config.py
AppCategorizer/main.py
AppCategorizer/category_processing/__init__.py
AppCategorizer/category_processing/processor.py
AppCategorizer/data_sources/__init__.py
AppCategorizer/data_sources/apple_store.py
AppCategorizer/data_sources/flathub.py
AppCategorizer/data_sources/gog.py
AppCategorizer/data_sources/itch_io.py
AppCategorizer/data_sources/myabandonware.py
AppCategorizer/data_sources/snap.py
AppCategorizer/data_sources/wikidata.py
AppCategorizer/ui/__init__.py
AppCategorizer/ui/interface.py
AppCategorizer/utils/__init__.py
AppCategorizer/utils/helpers.py
appcategorizer-1.0.0.dist-info/METADATA
appcategorizer-1.0.0.dist-info/WHEEL
appcategorizer-1.0.0.dist-info/entry_points.txt
appcategorizer-1.0.0.dist-info/top_level.txt
appcategorizer-1.0.0.dist-info/RECORD
