Metadata-Version: 2.4
Name: AppCategorizer
Version: 1.0.0
Summary: Application categorization tool using rule-based and AI methods
Author: Zain Ramzan
Requires-Python: >=3.7
Requires-Dist: beautifulsoup4
Requires-Dist: pandas
Requires-Dist: requests
Requires-Dist: selenium
Requires-Dist: transformers
Dynamic: author
Dynamic: description
Dynamic: description-content-type
Dynamic: requires-dist
Dynamic: requires-python
Dynamic: summary
